{
  "reportVersion": "2.1",
  "reportType": "sensor-batch",
  "generatedAt": "2026-06-19T07:40:13.261Z",
  "deviceInfo": {},
  "fieldType": "A",
  "summary": {
    "total": 1,
    "passed": 0,
    "failed": 1,
    "skipped": 0,
    "passRate": "0.0%"
  },
  "scenarios": [
    {
      "scenarioId": "T-ABNF-001",
      "scenarioName": "通信失败 ErRead 过滤",
      "conclusion": "异常",
      "skipReason": null,
      "duration": 70033,
      "assertionCount": 0,
      "failureCount": 0,
      "assertions": [],
      "inputs": null,
      "transactionLog": [],
      "cleanupResult": null
    }
  ]
}